<?xml version="1.0" encoding="UTF-8"?>
<MF0 version="1.1" packageUris="http://schema.mathworks.com/mf0/sl_modelref_info/R2020a http://schema.mathworks.com/mf0/slexec_mm_sto/R2019b_201902271317">
  <ModelRefInfoRepo.ModelRefInfoRoot type="ModelRefInfoRepo.ModelRefInfoRoot" uuid="5685725a-c10b-4904-b4f7-9873d13eb6bd">
    <autoSolverStatusFlags>333</autoSolverStatusFlags>
    <childModelRefInfo type="ModelRefInfoRepo.ChildModelRefInfo" uuid="e050064b-4447-4e2c-9ca6-27990bcf1cfe">
      <modelName>ELADRC_Model</modelName>
      <modelPath>ELADRC_Model</modelPath>
    </childModelRefInfo>
    <dataTransferInfos>AAFJTQAAAAAOAAAAOAAAAAYAAAAIAAAAAgAAAAAAAAAFAAAACAAAAAAAAAABAAAAAQAAAAAAAAAFAAQAAQAAAAEAAAAAAAAA</dataTransferInfos>
    <defaultsCMapping>{&quot;Inports&quot;:&quot;{\&quot;Name\&quot;:\&quot;Default\&quot;,\&quot;Checksum\&quot;:\&quot;Default\&quot;,\&quot;PerInstancePropertiesChecksum\&quot;:\&quot;\&quot;,\&quot;MemorySectionName\&quot;:\&quot;\&quot;,\&quot;MemorySectionChecksum\&quot;:\&quot;\&quot;}&quot;,&quot;Outports&quot;:&quot;{\&quot;Name\&quot;:\&quot;Default\&quot;,\&quot;Checksum\&quot;:\&quot;Default\&quot;,\&quot;PerInstancePropertiesChecksum\&quot;:\&quot;\&quot;,\&quot;MemorySectionName\&quot;:\&quot;\&quot;,\&quot;MemorySectionChecksum\&quot;:\&quot;\&quot;}&quot;,&quot;LocalParameters&quot;:&quot;{\&quot;Name\&quot;:\&quot;Default\&quot;,\&quot;Checksum\&quot;:\&quot;Default\&quot;,\&quot;PerInstancePropertiesChecksum\&quot;:\&quot;\&quot;,\&quot;MemorySectionName\&quot;:\&quot;\&quot;,\&quot;MemorySectionChecksum\&quot;:\&quot;\&quot;}&quot;,&quot;ParameterArguments&quot;:&quot;{\&quot;Name\&quot;:\&quot;Default\&quot;,\&quot;Checksum\&quot;:\&quot;Default\&quot;,\&quot;PerInstancePropertiesChecksum\&quot;:\&quot;\&quot;,\&quot;MemorySectionName\&quot;:\&quot;None\&quot;,\&quot;MemorySectionChecksum\&quot;:\&quot;None\&quot;}&quot;,&quot;GlobalParameters&quot;:&quot;{\&quot;Name\&quot;:\&quot;Default\&quot;,\&quot;Checksum\&quot;:\&quot;Default\&quot;,\&quot;PerInstancePropertiesChecksum\&quot;:\&quot;\&quot;,\&quot;MemorySectionName\&quot;:\&quot;\&quot;,\&quot;MemorySectionChecksum\&quot;:\&quot;\&quot;}&quot;,&quot;SharedLocalDataStores&quot;:&quot;{\&quot;Name\&quot;:\&quot;Default\&quot;,\&quot;Checksum\&quot;:\&quot;Default\&quot;,\&quot;PerInstancePropertiesChecksum\&quot;:\&quot;\&quot;,\&quot;MemorySectionName\&quot;:\&quot;None\&quot;,\&quot;MemorySectionChecksum\&quot;:\&quot;None\&quot;}&quot;,&quot;GlobalDataStores&quot;:&quot;{\&quot;Name\&quot;:\&quot;Default\&quot;,\&quot;Checksum\&quot;:\&quot;Default\&quot;,\&quot;PerInstancePropertiesChecksum\&quot;:\&quot;\&quot;,\&quot;MemorySectionName\&quot;:\&quot;None\&quot;,\&quot;MemorySectionChecksum\&quot;:\&quot;None\&quot;}&quot;,&quot;InternalData&quot;:&quot;{\&quot;Name\&quot;:\&quot;Default\&quot;,\&quot;Checksum\&quot;:\&quot;Default\&quot;,\&quot;PerInstancePropertiesChecksum\&quot;:\&quot;\&quot;,\&quot;MemorySectionName\&quot;:\&quot;\&quot;,\&quot;MemorySectionChecksum\&quot;:\&quot;\&quot;}&quot;,&quot;Constants&quot;:&quot;{\&quot;Name\&quot;:\&quot;Default\&quot;,\&quot;Checksum\&quot;:\&quot;Default\&quot;,\&quot;PerInstancePropertiesChecksum\&quot;:\&quot;\&quot;,\&quot;MemorySectionName\&quot;:\&quot;\&quot;,\&quot;MemorySectionChecksum\&quot;:\&quot;\&quot;}&quot;,&quot;DataTransfers&quot;:&quot;{\&quot;Name\&quot;:\&quot;Default\&quot;,\&quot;Checksum\&quot;:\&quot;Default\&quot;,\&quot;PerInstancePropertiesChecksum\&quot;:\&quot;\&quot;,\&quot;MemorySectionName\&quot;:\&quot;None\&quot;,\&quot;MemorySectionChecksum\&quot;:\&quot;None\&quot;}&quot;,&quot;ModelData&quot;:&quot;{\&quot;Name\&quot;:\&quot;Default\&quot;,\&quot;Checksum\&quot;:\&quot;Default\&quot;,\&quot;PerInstancePropertiesChecksum\&quot;:\&quot;\&quot;,\&quot;MemorySectionName\&quot;:\&quot;None\&quot;,\&quot;MemorySectionChecksum\&quot;:\&quot;None\&quot;}&quot;,&quot;InitializeTerminate&quot;:&quot;{\&quot;Name\&quot;:\&quot;Default\&quot;,\&quot;Checksum\&quot;:\&quot;Default\&quot;,\&quot;PerInstancePropertiesChecksum\&quot;:\&quot;\&quot;,\&quot;MemorySectionName\&quot;:\&quot;\&quot;,\&quot;MemorySectionChecksum\&quot;:\&quot;\&quot;}&quot;,&quot;Execution&quot;:&quot;{\&quot;Name\&quot;:\&quot;Default\&quot;,\&quot;Checksum\&quot;:\&quot;Default\&quot;,\&quot;PerInstancePropertiesChecksum\&quot;:\&quot;\&quot;,\&quot;MemorySectionName\&quot;:\&quot;\&quot;,\&quot;MemorySectionChecksum\&quot;:\&quot;\&quot;}&quot;,&quot;SharedUtility&quot;:&quot;{\&quot;Name\&quot;:\&quot;Default\&quot;,\&quot;Checksum\&quot;:\&quot;Default\&quot;,\&quot;PerInstancePropertiesChecksum\&quot;:\&quot;\&quot;,\&quot;MemorySectionName\&quot;:\&quot;\&quot;,\&quot;MemorySectionChecksum\&quot;:\&quot;\&quot;}&quot;}</defaultsCMapping>
    <hasBwsAccessed>true</hasBwsAccessed>
    <hasBwsAccessedByAnyModel>true</hasBwsAccessedByAnyModel>
    <hasContinuousSampleTime>true</hasContinuousSampleTime>
    <hasNonVirtualParameterChangeEvents>true</hasNonVirtualParameterChangeEvents>
    <loggingSaveFormat>2</loggingSaveFormat>
    <maxFreqHz>-1</maxFreqHz>
    <runtimeNonFcnCallRateInfos type="ModelRefInfoRepo.RateInfo">
      <compiled>true</compiled>
      <period>0</period>
      <priority>40</priority>
      <rateIdx>0</rateIdx>
    </runtimeNonFcnCallRateInfos>
    <sFcnInfo type="ModelRefInfoRepo.SFcnInformation" uuid="d12d922c-8957-4303-97a4-7df4fbe27c38">
      <blockSID>ELADRC_Model:3</blockSID>
      <expectsSeparateComplex>true</expectsSeparateComplex>
      <mexPath>C:\Users\Bryan\Desktop\SKML\CMEX_ELADRC\INVERTER.mexw64</mexPath>
      <name>INVERTER</name>
      <willBeDynamicallyLoaded>true</willBeDynamicallyLoaded>
    </sFcnInfo>
    <sampleTimeInheritanceRule>2</sampleTimeInheritanceRule>
    <timingAndTaskingRegistry>&lt;?xml version=&quot;1.0&quot;?&gt;
&lt;slexec_sto version=&quot;1.1&quot; packageUris=&quot;http://schema.mathworks.com/mf0/slexec_mm_sto/R2019b_201902271317&quot;&gt;
  &lt;sto.Registry type=&quot;sto.Registry&quot; uuid=&quot;0934e94c-df08-4078-9de2-148fbd4f0480&quot;&gt;
    &lt;clocks type=&quot;sto.Timer&quot; uuid=&quot;5121d0d4-a2f9-46cb-82f9-ff4ed59de5e7&quot;&gt;
      &lt;needsToProvideTimeDuringExecution&gt;true&lt;/needsToProvideTimeDuringExecution&gt;
      &lt;clockDomain type=&quot;sto.ClockDomain&quot; uuid=&quot;e745e663-216c-4590-9ec4-8c0d9129dd9d&quot;&gt;
        &lt;baseTaskID&gt;_task0&lt;/baseTaskID&gt;
        &lt;computedFundamentalStepSize&gt;0.20000000000000001&lt;/computedFundamentalStepSize&gt;
        &lt;rates type=&quot;sto.Rate&quot; uuid=&quot;c0e5b3d1-c66e-4c85-9b7b-c2828edc8ca2&quot;/&gt;
        &lt;rates type=&quot;sto.Rate&quot; uuid=&quot;63790713-72f7-41ff-b2b8-36238b9ffa77&quot;/&gt;
        &lt;rootTaskHierarchyElements type=&quot;sto.Task&quot; uuid=&quot;9fc39383-0099-474f-9e3b-645f17f2865c&quot;&gt;
          &lt;isExecutable&gt;true&lt;/isExecutable&gt;
          &lt;orderIndex&gt;1&lt;/orderIndex&gt;
          &lt;rates type=&quot;sto.Rate&quot; uuid=&quot;c0e5b3d1-c66e-4c85-9b7b-c2828edc8ca2&quot;&gt;
            &lt;annotation&gt;Cont&lt;/annotation&gt;
            &lt;description&gt;Continuous&lt;/description&gt;
            &lt;eventSourceType&gt;UNSPECIFIED_EVENT_SOURCE&lt;/eventSourceType&gt;
            &lt;registry type=&quot;sto.Registry&quot; uuid=&quot;0934e94c-df08-4078-9de2-148fbd4f0480&quot;/&gt;
            &lt;taskId&gt;_task0&lt;/taskId&gt;
            &lt;rateSpec type=&quot;sto.RateSpec&quot; uuid=&quot;2a97206d-60b7-4292-b273-9ab7b2a963db&quot;/&gt;
          &lt;/rates&gt;
          &lt;rates type=&quot;sto.Rate&quot; uuid=&quot;63790713-72f7-41ff-b2b8-36238b9ffa77&quot;&gt;
            &lt;annotation&gt;FiM&lt;/annotation&gt;
            &lt;colorIndex&gt;8&lt;/colorIndex&gt;
            &lt;description&gt;Fixed in Minor Step&lt;/description&gt;
            &lt;eventSourceType&gt;UNSPECIFIED_EVENT_SOURCE&lt;/eventSourceType&gt;
            &lt;rateIDX&gt;-1&lt;/rateIDX&gt;
            &lt;registry type=&quot;sto.Registry&quot; uuid=&quot;0934e94c-df08-4078-9de2-148fbd4f0480&quot;/&gt;
            &lt;taskId&gt;_task0&lt;/taskId&gt;
            &lt;useForExecution&gt;NotForExecution&lt;/useForExecution&gt;
            &lt;rateSpec type=&quot;sto.RateSpec&quot; uuid=&quot;6ec5d40c-2efc-4ff4-9303-1b730b103a1d&quot;&gt;
              &lt;offset&gt;1&lt;/offset&gt;
              &lt;rateType&gt;ZOHContinuous&lt;/rateType&gt;
            &lt;/rateSpec&gt;
          &lt;/rates&gt;
          &lt;elementType&gt;Task&lt;/elementType&gt;
          &lt;identifier&gt;_task0&lt;/identifier&gt;
          &lt;priority&gt;40&lt;/priority&gt;
        &lt;/rootTaskHierarchyElements&gt;
      &lt;/clockDomain&gt;
    &lt;/clocks&gt;
    &lt;clocks type=&quot;sto.Event&quot; uuid=&quot;71314d8b-67aa-4990-99c8-982edb765752&quot;&gt;
      &lt;eventType&gt;PARAMETER_CHANGE_EVENT&lt;/eventType&gt;
      &lt;cNum&gt;1&lt;/cNum&gt;
      &lt;clockType&gt;Event&lt;/clockType&gt;
      &lt;identifier&gt;ParameterChangeEvent&lt;/identifier&gt;
      &lt;resolution&gt;-1&lt;/resolution&gt;
      &lt;specifiedTaskingMode&gt;ExplicitTasking&lt;/specifiedTaskingMode&gt;
      &lt;timeAdvanceMode&gt;None&lt;/timeAdvanceMode&gt;
      &lt;clockDomain type=&quot;sto.ClockDomain&quot; uuid=&quot;c7a59064-09ff-4fc0-87ef-7572e8621ed2&quot;&gt;
        &lt;computedFundamentalStepSize&gt;-1&lt;/computedFundamentalStepSize&gt;
        &lt;rates type=&quot;sto.Rate&quot; uuid=&quot;c22f96e5-ea02-41cd-bae8-49f743a6d4f2&quot;/&gt;
        &lt;rootTaskHierarchyElements type=&quot;sto.Task&quot; uuid=&quot;9644818a-4579-4d13-bf1e-991aedf739c0&quot;&gt;
          &lt;isExecutable&gt;true&lt;/isExecutable&gt;
          &lt;isExplicit&gt;true&lt;/isExplicit&gt;
          &lt;rates type=&quot;sto.Rate&quot; uuid=&quot;c22f96e5-ea02-41cd-bae8-49f743a6d4f2&quot;&gt;
            &lt;annotation&gt;Inf&lt;/annotation&gt;
            &lt;colorIndex&gt;6&lt;/colorIndex&gt;
            &lt;description&gt;Constant&lt;/description&gt;
            &lt;eventSourceType&gt;PARAMETER_CHANGE_EVENT&lt;/eventSourceType&gt;
            &lt;rateIDX&gt;1&lt;/rateIDX&gt;
            &lt;registry type=&quot;sto.Registry&quot; uuid=&quot;0934e94c-df08-4078-9de2-148fbd4f0480&quot;/&gt;
            &lt;stringID&gt;ParameterChangeEvent&lt;/stringID&gt;
            &lt;taskId&gt;ModelWideParameterChangeEvent&lt;/taskId&gt;
            &lt;rateSpec type=&quot;sto.RateSpec&quot; uuid=&quot;06f3bfd7-0113-49eb-be9c-b9c5aaec1ba4&quot;&gt;
              &lt;period&gt;inf&lt;/period&gt;
              &lt;rateType&gt;ModelWideParameterChangeEvent&lt;/rateType&gt;
            &lt;/rateSpec&gt;
          &lt;/rates&gt;
          &lt;tNum&gt;1&lt;/tNum&gt;
          &lt;elementType&gt;Task&lt;/elementType&gt;
          &lt;identifier&gt;ModelWideParameterChangeEvent&lt;/identifier&gt;
          &lt;priority&gt;-1&lt;/priority&gt;
          &lt;schedulingClockID&gt;ParameterChangeEvent&lt;/schedulingClockID&gt;
        &lt;/rootTaskHierarchyElements&gt;
      &lt;/clockDomain&gt;
    &lt;/clocks&gt;
    &lt;executionSpec&gt;Undetermined&lt;/executionSpec&gt;
    &lt;hasUnknownEdges&gt;true&lt;/hasUnknownEdges&gt;
    &lt;taskDependencyGraph type=&quot;sto.SerializedTaskConnectionList&quot; uuid=&quot;5476610a-bfe3-472d-9c3f-fe382794addc&quot;&gt;
      &lt;taskIdentifier&gt;_task0&lt;/taskIdentifier&gt;
    &lt;/taskDependencyGraph&gt;
    &lt;taskDependencyGraph type=&quot;sto.SerializedTaskConnectionList&quot; uuid=&quot;dafa8e21-5f34-4c59-9aff-6e1907266360&quot;&gt;
      &lt;clockIdentifier&gt;ParameterChangeEvent&lt;/clockIdentifier&gt;
      &lt;serializedConnectionProperties type=&quot;sto.SerializedConnectionProperties&quot; uuid=&quot;83e2e12a-eec5-485f-9090-41bc98f0169c&quot;&gt;
        &lt;targetTaskIdentifier&gt;_task0&lt;/targetTaskIdentifier&gt;
      &lt;/serializedConnectionProperties&gt;
      &lt;taskIdentifier&gt;ModelWideParameterChangeEvent&lt;/taskIdentifier&gt;
    &lt;/taskDependencyGraph&gt;
    &lt;taskPriorityDirection&gt;HighNumberLast&lt;/taskPriorityDirection&gt;
    &lt;tasks type=&quot;sto.Task&quot; uuid=&quot;9fc39383-0099-474f-9e3b-645f17f2865c&quot;/&gt;
    &lt;tasks type=&quot;sto.Task&quot; uuid=&quot;9644818a-4579-4d13-bf1e-991aedf739c0&quot;/&gt;
  &lt;/sto.Registry&gt;
&lt;/slexec_sto&gt;</timingAndTaskingRegistry>
    <FMUBlockMap type="ModelRefInfoRepo.FMUBlockInfo" uuid="ab156550-70cd-4a0a-b249-6268becafaf5"/>
    <codeGenInfo type="ModelRefInfoRepo.CodeGenInformation" uuid="e1a29b82-6443-45d0-af6a-60154234a250"/>
    <configSettingsForConsistencyChecks type="ModelRefInfoRepo.ConfigSettingsForConsistencyChecks" uuid="48346991-a0bb-4ea7-817a-af883c3d41b6">
      <consistentOutportInitialization>true</consistentOutportInitialization>
      <frameDiagnosticSetting>2</frameDiagnosticSetting>
      <signalLoggingSaveFormat>2</signalLoggingSaveFormat>
      <solverName>VariableStepDiscrete</solverName>
      <hardwareSettings type="ModelRefInfoRepo.HardwareSettings" uuid="7bea942e-cdb7-4a1e-99f6-a30daef26ef1">
        <prodBitPerChar>8</prodBitPerChar>
        <prodBitPerDouble>64</prodBitPerDouble>
        <prodBitPerFloat>32</prodBitPerFloat>
        <prodBitPerInt>32</prodBitPerInt>
        <prodBitPerLong>32</prodBitPerLong>
        <prodBitPerLongLong>64</prodBitPerLongLong>
        <prodBitPerPointer>64</prodBitPerPointer>
        <prodBitPerPtrDiffT>64</prodBitPerPtrDiffT>
        <prodBitPerShort>16</prodBitPerShort>
        <prodBitPerSizeT>64</prodBitPerSizeT>
        <prodEndianess>1</prodEndianess>
        <prodShiftRight>true</prodShiftRight>
        <prodWordSize>64</prodWordSize>
      </hardwareSettings>
    </configSettingsForConsistencyChecks>
    <controllableInputRatesMap type="ModelRefInfoRepo.VarTsUIDMap" uuid="1eb7685a-b9c8-4f75-bdb1-119c58e3b43e"/>
    <controllableOutputRatesMap type="ModelRefInfoRepo.VarTsUIDMap" uuid="6f5b4048-bfbe-4d44-a057-0d1d4214bb51"/>
    <dataPortGroup type="ModelRefInfoRepo.DataPortGroup" uuid="8583e138-1f3d-43cf-8c24-a61cca10317d"/>
    <interfaceParameterInfo type="ModelRefInfoRepo.InterfaceParameterInfo" uuid="fa356fbf-0fa0-4764-8eec-1ff4c9be576a"/>
    <messageInfo type="ModelRefInfoRepo.MessageInformation" uuid="c5bdda97-63d1-4956-90ea-559a67ed4e85"/>
    <methodInfo type="ModelRefInfoRepo.MethodExistenceInfo" uuid="3e223dbf-af37-4faa-a10f-731f8ca48df8">
      <hasDisableMethod>true</hasDisableMethod>
      <hasSystemInitializeMethod>true</hasSystemInitializeMethod>
      <hasTerminateMethod>true</hasTerminateMethod>
    </methodInfo>
    <periodicEventPortUnsupportedBlockInfo type="ModelRefInfoRepo.PeriodicEventPortUnsupportedBlockInfo" uuid="9e372e9c-9772-4ea7-b17c-b60da3437166"/>
    <portGroupsRequireSameRate type="ModelRefInfoRepo.PortGroupsRequireSameRate" uuid="0c9c0907-4893-4b6b-99f6-083447a35ac5">
      <DSMPortGroups type="ModelRefInfoRepo.NameToPortGroupIdxVectMap" uuid="16ff4668-ce0e-437a-a215-81ef53d836c3"/>
      <GlobalDSMPortGroups type="ModelRefInfoRepo.NameToPortGroupIdxVectMap" uuid="c1b4abbf-5511-47d2-b311-39cc99995e6c"/>
      <mergedPortGroups type="ModelRefInfoRepo.NameToPortGroupIdxVectMap" uuid="cbe35d52-270c-4ec4-acc7-8e1b71a75598"/>
    </portGroupsRequireSameRate>
    <rateSpecOfGlobalDSMAccessedByDescExpFcnMdlMap type="ModelRefInfoRepo.GlobalDSMRateSpecMap" uuid="1328bf25-953f-4686-9f86-a294d057127f"/>
    <simulinkFunctions type="ModelRefInfoRepo.SimulinkFunctions" uuid="836fcbf3-1de0-4d08-aba6-b2932e41b16c">
      <compSimulinkFunctionCatalog></compSimulinkFunctionCatalog>
      <variantSimulinkFunctions type="ModelRefInfoRepo.VariantSimulinkFunctions" uuid="d0221d6a-1c19-4fa4-9c1b-f006dd7d0ab3"/>
    </simulinkFunctions>
    <stateWriterToOwnerMap type="ModelRefInfoRepo.StateWriterInfo" uuid="647063c6-d1fe-415c-ba9e-b7873cef68cb"/>
    <stoClientDataRegistry type="sto.ClientDataRegistry" uuid="7898d4e1-447b-4ed1-820c-13b6a18a42ad">
      <dataSets type="sto.ClientClockNamedDataSet" uuid="224f1b13-2b25-4381-ad3b-4954da635449">
        <tag>sltpEvents</tag>
      </dataSets>
      <dataSets type="sto.ClientTaskHierarchyElementNamedDataSet" uuid="522e7770-b249-4014-9bb4-890bfccf8fb9">
        <tag>sltpTaskGroups</tag>
      </dataSets>
      <dataSets type="sto.ClientTaskHierarchyElementNamedDataSet" uuid="7e3aa7fc-8cd1-490c-8581-d223b0a378c8">
        <dSet type="ModelRefInfoRepo.SltpTaskData" uuid="d853f2ae-d4f2-4df5-b6bc-f5816152da88"/>
        <tSet type="ModelRefInfoRepo.SltpTaskData" uuid="d853f2ae-d4f2-4df5-b6bc-f5816152da88">
          <dataName>Cont</dataName>
          <linkedSet type="sto.ClientTaskHierarchyElementNamedDataSet" uuid="7e3aa7fc-8cd1-490c-8581-d223b0a378c8"/>
          <id type="sto.TaskHierarchyElementId">
            <id>_task0</id>
          </id>
        </tSet>
        <tag>sltpTasks</tag>
      </dataSets>
    </stoClientDataRegistry>
    <varTsUIDMap type="ModelRefInfoRepo.VarTsUIDMap" uuid="2e3012af-363c-41d3-a54e-9dad69827c6b"/>
  </ModelRefInfoRepo.ModelRefInfoRoot>
</MF0>